<?xml version="1.0" encoding="UTF-8"?>
<metadata xml:lang="es"><Esri><CreaDate>20221205</CreaDate><CreaTime>20504900</CreaTime><ArcGISFormat>1.0</ArcGISFormat><SyncOnce>TRUE</SyncOnce><DataProperties><lineage><Process ToolSource="c:\program files (x86)\arcgis\desktop10.8\ArcToolbox\Toolboxes\Spatial Analyst Tools.tbx\ExtractByMask" Date="20221205" Time="205049">ExtractByMask Geo.tif La_Friso "C:\Users\SANTIAGO CORREA\Desktop\Universidad\Cartografía Geo\Git\Cartografia_Geotecnica\Taller 5\Colaboratory\Geología.tif"</Process></lineage></DataProperties></Esri></metadata>
