<?xml version="1.0" encoding="UTF-8"?>
<metadata xml:lang="es"><Esri><CreaDate>20220909</CreaDate><CreaTime>22210400</CreaTime><ArcGISFormat>1.0</ArcGISFormat><SyncOnce>TRUE</SyncOnce><DataProperties><lineage><Process ToolSource="c:\program files (x86)\arcgis\desktop10.8\ArcToolbox\Toolboxes\Spatial Analyst Tools.tbx\FlowAccumulation" Date="20220909" Time="222104">FlowAccumulation FD.tif "C:\Users\SANTIAGO CORREA\Desktop\Cartografía Geo\Taller 2\DEM\5X5\FA.tif" # FLOAT D8</Process></lineage></DataProperties></Esri></metadata>
